tabulate/__init__.py
tabulate/core.py
columnator-0.1.1.dist-info/METADATA
columnator-0.1.1.dist-info/WHEEL
columnator-0.1.1.dist-info/top_level.txt
columnator-0.1.1.dist-info/RECORD
