Metadata-Version: 2.4
Name: columnator
Version: 0.1.1
Summary: Una librería simple para formatear listas en tablas.
Home-page: https://github.com/PanecilloPY/Columnator
Author: Maxim Rebollo
Author-email: maximrebollosablonh@gmail.com
Classifier: Programming Language :: Python :: 3
Classifier: License :: OSI Approved :: MIT License
Classifier: Operating System :: OS Independent
Requires-Python: >=3.6
Dynamic: author
Dynamic: author-email
Dynamic: classifier
Dynamic: description
Dynamic: description-content-type
Dynamic: home-page
Dynamic: requires-python
Dynamic: summary
